.gitignore
LICENSE
Makefile
README.md
circle.yml
setup.cfg
setup.py
tox.ini
scrapy_datadog.egg-info/PKG-INFO
scrapy_datadog.egg-info/SOURCES.txt
scrapy_datadog.egg-info/dependency_links.txt
scrapy_datadog.egg-info/requires.txt
scrapy_datadog.egg-info/top_level.txt
scrapydatadog/__init__.py
scrapydatadog/extension.py
scrapydatadog/settings.py
scrapydatadog/utils.py
tests/test_extension.py